mangum/__init__.py
mangum/adapter.py
mangum/exceptions.py
mangum/py.typed
mangum/types.py
mangum/handlers/__init__.py
mangum/handlers/alb.py
mangum/handlers/api_gateway.py
mangum/handlers/lambda_at_edge.py
mangum/handlers/utils.py
mangum/protocols/__init__.py
mangum/protocols/http.py
mangum/protocols/lifespan.py
mangum-0.16.0.dist-info/LICENSE
mangum-0.16.0.dist-info/METADATA
mangum-0.16.0.dist-info/WHEEL
mangum-0.16.0.dist-info/top_level.txt
mangum-0.16.0.dist-info/RECORD
