Metadata-Version: 2.1
Name: mangum
Version: 0.16.0
Summary: AWS Lambda support for ASGI applications
Home-page: https://github.com/jordaneremieff/mangum
Author: Jordan Eremieff
Author-email: jordan@eremieff.com
License: MIT
Platform: UNKNOWN
Classifier: License :: OSI Approved :: MIT License
Classifier: Operating System :: OS Independent
Classifier: Programming Language :: Python
Classifier: Programming Language :: Python :: 3.7
Classifier: Programming Language :: Python :: 3.8
Classifier: Programming Language :: Python :: 3.9
Classifier: Programming Language :: Python :: 3.10
Requires-Python: >=3.7
